CHANGES.txt
README.txt
bootstrap.py
buildout.cfg
setup.py
src/z3c/__init__.py
src/z3c.recipe.paster.egg-info/PKG-INFO
src/z3c.recipe.paster.egg-info/SOURCES.txt
src/z3c.recipe.paster.egg-info/dependency_links.txt
src/z3c.recipe.paster.egg-info/entry_points.txt
src/z3c.recipe.paster.egg-info/namespace_packages.txt
src/z3c.recipe.paster.egg-info/requires.txt
src/z3c.recipe.paster.egg-info/top_level.txt
src/z3c/recipe/__init__.py
src/z3c/recipe/paster/README.txt
src/z3c/recipe/paster/__init__.py
src/z3c/recipe/paster/debug.py
src/z3c/recipe/paster/debug.txt
src/z3c/recipe/paster/paster.py
src/z3c/recipe/paster/paster.txt
src/z3c/recipe/paster/serve.py
src/z3c/recipe/paster/tests.py
src/z3c/recipe/paster/wsgi.py